django_adobesign/__init__.py
django_adobesign/api.py
django_adobesign/backend.py
django_adobesign/client.py
django_adobesign/exceptions.py
django_adobesign/views.py
django_adobesign/tests/__init__.py
django_adobesign/tests/test_adobe_backend.py
django_adobesign/tests/test_adobe_client.py
django_adobesign-0.12.dist-info/AUTHORS
django_adobesign-0.12.dist-info/METADATA
django_adobesign-0.12.dist-info/WHEEL
django_adobesign-0.12.dist-info/top_level.txt
django_adobesign-0.12.dist-info/zip-safe
django_adobesign-0.12.dist-info/RECORD
