Metadata-Version: 2.1
Name: django-adobesign
Version: 0.12
Summary: Django application to manage online signature with AdobeSign.
Home-page: http://github.com/peopledoc/django-adobesign
Author: Peopledoc
Author-email: david.steinberger@people-doc.com
License: UNKNOWN
Keywords: peopledoc anysign adobesign
Platform: UNKNOWN
Classifier: Operating System :: POSIX
Classifier: Framework :: Django
Classifier: Framework :: Django :: 2.2
Classifier: Framework :: Django :: 3.2
Classifier: Programming Language :: Python :: 3
Classifier: Programming Language :: Python :: 3.7
Classifier: Programming Language :: Python :: 3.8
License-File: AUTHORS
Requires-Dist: Django (<3.3,>=2.2.27)
Requires-Dist: django-anysign (>=1.2)
Requires-Dist: requests
Requires-Dist: requests-oauthlib (<1.2.0)
